whois_vu/__init__.py
whois_vu/adataclasses.py
whois_vu/api.py
whois_vu/atypes.py
whois_vu/errors.py
whois_vu-0.3.0.dist-info/WHEEL
whois_vu-0.3.0.dist-info/METADATA
whois_vu-0.3.0.dist-info/RECORD
