Metadata-Version: 2.1
Name: whois-vu
Version: 0.3.0
Summary: Synchronous python wrapper for api.whois.vu
Author: kiriharu
Author-email: kiriharu@yandex.ru
Requires-Python: >=3.7,<4.0
Classifier: Programming Language :: Python :: 3
Classifier: Programming Language :: Python :: 3.7
Classifier: Programming Language :: Python :: 3.8
Classifier: Programming Language :: Python :: 3.9
Requires-Dist: requests (>=2.25.1,<3.0.0)
